EULANGS/EULANGS.py
EULANGS/__init__.py
EULANGS-1.0.2.dist-info/LICENSE.txt
EULANGS-1.0.2.dist-info/METADATA
EULANGS-1.0.2.dist-info/WHEEL
EULANGS-1.0.2.dist-info/top_level.txt
EULANGS-1.0.2.dist-info/RECORD
